LICENSE
MANIFEST.in
README.rst
setup.py
admin_monitoring/__init__.py
admin_monitoring/admin.py
admin_monitoring/utils.py
admin_monitoring/templatetags/__init__.py
admin_monitoring/templatetags/admin_monitoring_tags.py
django_admin_monitoring.egg-info/PKG-INFO
django_admin_monitoring.egg-info/SOURCES.txt
django_admin_monitoring.egg-info/dependency_links.txt
django_admin_monitoring.egg-info/top_level.txt